version.py
deriva_client-1.7.9.dist-info/licenses/LICENSE
deriva_client-1.7.9.dist-info/METADATA
deriva_client-1.7.9.dist-info/WHEEL
deriva_client-1.7.9.dist-info/top_level.txt
deriva_client-1.7.9.dist-info/RECORD
