Metadata-Version: 2.4
Name: deriva-client
Version: 1.7.9
Summary: A Python-based application suite of client software for use with the DERIVA platform.
Home-page: https://github.com/informatics-isi-edu/deriva-client
Author: USC Information Sciences Institute, Informatics Systems Research Division
Author-email: isrd-support@isi.edu
Maintainer: USC Information Sciences Institute, Informatics Systems Research Division
Maintainer-email: isrd-support@isi.edu
License: GNU GPL 3.0
Classifier: Intended Audience :: Science/Research
Classifier: Intended Audience :: Developers
Classifier: License :: OSI Approved :: GNU General Public License v3 (GPLv3)
Classifier: Operating System :: POSIX
Classifier: Operating System :: MacOS :: MacOS X
Classifier: Operating System :: Microsoft :: Windows
Classifier: Programming Language :: Python
Classifier: Programming Language :: Python :: 3.8
Classifier: Programming Language :: Python :: 3.9
Classifier: Programming Language :: Python :: 3.10
Classifier: Programming Language :: Python :: 3.11
Classifier: Programming Language :: Python :: 3.12
Requires-Python: >=3.8
License-File: LICENSE
Requires-Dist: bdbag[boto]==1.7.5
Requires-Dist: globus_sdk<4,>=3
Requires-Dist: minid==2.0.1
Requires-Dist: fair-research-login==0.3.1
Requires-Dist: fair-identifiers-client==0.5.1
Requires-Dist: deriva==1.7.9
Requires-Dist: deriva-qt==1.7.9
Requires-Dist: deriva-workbench==0.1.2
Requires-Dist: bdbag_gui==1.2.1
Requires-Dist: PyQtWebEngine==5.15.5
Dynamic: author
Dynamic: author-email
Dynamic: classifier
Dynamic: description
Dynamic: description-content-type
Dynamic: home-page
Dynamic: license
Dynamic: license-file
Dynamic: maintainer
Dynamic: maintainer-email
Dynamic: requires-dist
Dynamic: requires-python
Dynamic: summary
